nomad_schema_plugin_simulation_workflow-1.0.10.dist-info/licenses/LICENSE
simulationworkflowschema/__init__.py
simulationworkflowschema/chemical_reaction.py
simulationworkflowschema/dmft.py
simulationworkflowschema/elastic.py
simulationworkflowschema/equation_of_state.py
simulationworkflowschema/general.py
simulationworkflowschema/geometry_optimization.py
simulationworkflowschema/gw.py
simulationworkflowschema/max_ent.py
simulationworkflowschema/molecular_dynamics.py
simulationworkflowschema/nomad_plugin.yaml
simulationworkflowschema/phonon.py
simulationworkflowschema/photon_polarization.py
simulationworkflowschema/single_point.py
simulationworkflowschema/tb.py
simulationworkflowschema/thermodynamics.py
simulationworkflowschema/xs.py
nomad_schema_plugin_simulation_workflow-1.0.10.dist-info/METADATA
nomad_schema_plugin_simulation_workflow-1.0.10.dist-info/WHEEL
nomad_schema_plugin_simulation_workflow-1.0.10.dist-info/entry_points.txt
nomad_schema_plugin_simulation_workflow-1.0.10.dist-info/top_level.txt
nomad_schema_plugin_simulation_workflow-1.0.10.dist-info/RECORD
