Metadata-Version: 2.4
Name: nomad-schema-plugin-simulation-workflow
Version: 1.0.10
Summary: Simulation workflow schema plugin for NOMAD.
Author: The NOMAD Authors
License: Apache-2.0
Project-URL: homepage, https://github.com/nomad-coe/nomad-schema-plugin-simulation-workflow
Requires-Python: >=3.9
License-File: LICENSE
Requires-Dist: nomad-lab>=1.3.13
Requires-Dist: nomad-schema-plugin-run>=1.0.1
Requires-Dist: mdanalysis<3.0.0,>=2.8.0; python_full_version >= "3.10"
Requires-Dist: mdanalysis<2.8; python_full_version < "3.10"
Requires-Dist: scipy>=1.7.1
Requires-Dist: networkx>=2.6.3
Dynamic: license-file
